{
  "id" : "DefinirNovasAlteracoes",
  "name" : "DefinirNovasAlteracoes",
  "type" : "form",
  "uuid" : "2cbb3ef3-1aa5-44f7-ac1c-abfeb169c9d4",
  "modelVersion" : "2.6",
  "lastUpdate" : 1781912831376,
  "description" : "Page generated with Bonita UI designer",
  "rows" : [
    [
      {
        "type" : "container",
        "dimension" : {
          "xs" : 12
        },
        "propertyValues" : { },
        "reference" : "d5265523-fc5c-4307-b06b-ff8723270bef",
        "hasValidationError" : false,
        "id" : "pbContainer",
        "rows" : [
          [
            {
              "type" : "component",
              "dimension" : {
                "md" : 12,
                "sm" : 12,
                "xs" : 12,
                "lg" : 12
              },
              "propertyValues" : {
                "hidden" : {
                  "type" : "constant",
                  "value" : false
                },
                "level" : {
                  "type" : "constant",
                  "value" : "Level 1"
                },
                "cssClasses" : {
                  "type" : "constant",
                  "value" : ""
                },
                "text" : {
                  "type" : "interpolation",
                  "value" : "{{ task.displayName }}"
                },
                "alignment" : {
                  "type" : "constant",
                  "value" : "center"
                },
                "dimension" : {
                  "type" : "constant",
                  "value" : 12
                }
              },
              "reference" : "41845d51-7ad1-40cb-a764-6c4e756e34d5",
              "hasValidationError" : false,
              "id" : "pbTitle",
              "description" : ""
            }
          ],
          [
            {
              "type" : "component",
              "dimension" : {
                "md" : 12,
                "sm" : 12,
                "xs" : 12,
                "lg" : 12
              },
              "propertyValues" : {
                "allowHtml" : {
                  "type" : "constant",
                  "value" : true
                },
                "labelHidden" : {
                  "type" : "constant",
                  "value" : true
                },
                "hidden" : {
                  "type" : "constant",
                  "value" : false
                },
                "cssClasses" : {
                  "type" : "constant",
                  "value" : ""
                },
                "label" : {
                  "type" : "interpolation"
                },
                "text" : {
                  "type" : "interpolation",
                  "value" : "{{ task.displayDescription }}"
                },
                "alignment" : {
                  "type" : "constant",
                  "value" : "left"
                },
                "dimension" : {
                  "type" : "constant",
                  "value" : 12
                }
              },
              "reference" : "c6070277-7366-4514-b944-19d8367c81e7",
              "hasValidationError" : false,
              "id" : "pbText",
              "description" : ""
            }
          ]
        ]
      }
    ],
    [
      {
        "type" : "formContainer",
        "dimension" : {
          "xs" : 12
        },
        "propertyValues" : {
          "cssClasses" : {
            "type" : "constant",
            "value" : ""
          },
          "hidden" : {
            "type" : "constant",
            "value" : false
          }
        },
        "reference" : "89bfd185-d75d-42c7-9ee0-2fa311350a92",
        "hasValidationError" : false,
        "id" : "pbFormContainer",
        "container" : {
          "type" : "container",
          "dimension" : {
            "xs" : 12
          },
          "propertyValues" : { },
          "reference" : "6f2c7f58-abf1-458b-a5ec-7d9f718cfebf",
          "hasValidationError" : false,
          "id" : "pbContainer",
          "rows" : [
            [
              {
                "type" : "component",
                "dimension" : {
                  "xs" : 12,
                  "sm" : 12,
                  "md" : 12,
                  "lg" : 12
                },
                "propertyValues" : {
                  "cssClasses" : {
                    "type" : "constant",
                    "value" : ""
                  },
                  "hidden" : {
                    "type" : "constant",
                    "value" : false
                  },
                  "allowHTML" : {
                    "type" : "constant",
                    "value" : false
                  },
                  "text" : {
                    "type" : "interpolation",
                    "value" : "Pedido de novas alterações"
                  },
                  "level" : {
                    "type" : "constant",
                    "value" : "Level 2"
                  },
                  "alignment" : {
                    "type" : "constant",
                    "value" : "left"
                  }
                },
                "reference" : "0263e4df-1d12-4385-8be2-7d88c0eb79c5",
                "hasValidationError" : false,
                "id" : "pbTitle"
              }
            ],
            [
              {
                "type" : "component",
                "dimension" : {
                  "md" : 12,
                  "sm" : 12,
                  "xs" : 12,
                  "lg" : 12
                },
                "propertyValues" : {
                  "hidden" : {
                    "type" : "constant",
                    "value" : false
                  },
                  "level" : {
                    "type" : "constant",
                    "value" : "Level 4"
                  },
                  "cssClasses" : {
                    "type" : "constant",
                    "value" : ""
                  },
                  "text" : {
                    "type" : "interpolation",
                    "value" : "O cliente não concordou com as alterções anterior, defina novas alterações funcionais."
                  },
                  "alignment" : {
                    "type" : "constant",
                    "value" : "left"
                  },
                  "dimension" : {
                    "type" : "constant",
                    "value" : 12
                  },
                  "allowHTML" : {
                    "type" : "constant",
                    "value" : false
                  }
                },
                "reference" : "4d845b2c-f23d-4253-8a8d-6b9477142c96",
                "hasValidationError" : false,
                "id" : "pbTitle",
                "description" : ""
              }
            ],
            [
              {
                "type" : "container",
                "dimension" : {
                  "md" : 12,
                  "sm" : 12,
                  "xs" : 12,
                  "lg" : 12
                },
                "propertyValues" : {
                  "repeatedCollection" : {
                    "type" : "variable"
                  },
                  "hidden" : {
                    "type" : "constant",
                    "value" : false
                  },
                  "cssClasses" : {
                    "type" : "constant",
                    "value" : ""
                  },
                  "dimension" : {
                    "type" : "constant",
                    "value" : 12
                  }
                },
                "reference" : "e0542b88-31c6-45e6-99b4-8474c488cf6e",
                "hasValidationError" : false,
                "id" : "pbContainer",
                "rows" : [
                  [
                    {
                      "type" : "component",
                      "dimension" : {
                        "md" : 12,
                        "sm" : 12,
                        "xs" : 12,
                        "lg" : 12
                      },
                      "propertyValues" : {
                        "labelHidden" : {
                          "type" : "constant",
                          "value" : false
                        },
                        "hidden" : {
                          "type" : "constant",
                          "value" : false
                        },
                        "labelPosition" : {
                          "type" : "constant",
                          "value" : "top"
                        },
                        "cssClasses" : {
                          "type" : "constant",
                          "value" : ""
                        },
                        "labelWidth" : {
                          "type" : "constant",
                          "value" : 1
                        },
                        "readOnly" : {
                          "type" : "constant",
                          "value" : false
                        },
                        "label" : {
                          "type" : "interpolation",
                          "value" : "Nova Alteração"
                        },
                        "placeholder" : {
                          "type" : "constant"
                        },
                        "type" : {
                          "type" : "constant",
                          "value" : "text"
                        },
                        "dimension" : {
                          "type" : "constant",
                          "value" : 12
                        },
                        "value" : {
                          "type" : "variable",
                          "value" : "pedido.alteracao"
                        },
                        "required" : {
                          "type" : "constant",
                          "value" : false
                        },
                        "allowHTML" : {
                          "type" : "constant",
                          "value" : false
                        },
                        "minLength" : {
                          "type" : "constant",
                          "value" : ""
                        },
                        "maxLength" : {
                          "type" : "constant",
                          "value" : ""
                        },
                        "debounce" : {
                          "type" : "constant",
                          "value" : 0
                        },
                        "min" : {
                          "type" : "constant"
                        },
                        "max" : {
                          "type" : "constant"
                        },
                        "step" : {
                          "type" : "constant",
                          "value" : 1
                        }
                      },
                      "reference" : "c2427e2b-1d71-42ef-b39f-87799ce6633e",
                      "hasValidationError" : false,
                      "id" : "pbInput",
                      "description" : ""
                    }
                  ]
                ]
              }
            ],
            [
              {
                "type" : "component",
                "dimension" : {
                  "md" : 12,
                  "sm" : 12,
                  "xs" : 12,
                  "lg" : 12
                },
                "propertyValues" : {
                  "removeItem" : {
                    "type" : "variable"
                  },
                  "hidden" : {
                    "type" : "constant",
                    "value" : false
                  },
                  "cssClasses" : {
                    "type" : "constant",
                    "value" : ""
                  },
                  "buttonStyle" : {
                    "type" : "constant",
                    "value" : "primary"
                  },
                  "label" : {
                    "type" : "interpolation",
                    "value" : "Submit"
                  },
                  "dataToSend" : {
                    "type" : "expression",
                    "value" : "formOutput"
                  },
                  "dataFromError" : {
                    "type" : "variable",
                    "value" : "formOutput._submitError"
                  },
                  "allowHTML" : {
                    "type" : "constant",
                    "value" : false
                  },
                  "labelHidden" : {
                    "type" : "constant",
                    "value" : false
                  },
                  "collectionPosition" : {
                    "type" : "constant"
                  },
                  "targetUrlOnSuccess" : {
                    "type" : "interpolation",
                    "value" : "/bonita"
                  },
                  "action" : {
                    "type" : "constant",
                    "value" : "Submit task"
                  },
                  "collectionToModify" : {
                    "type" : "variable"
                  },
                  "valueToAdd" : {
                    "type" : "expression"
                  },
                  "disabled" : {
                    "type" : "expression",
                    "value" : "$form.$invalid"
                  },
                  "alignment" : {
                    "type" : "constant",
                    "value" : "center"
                  },
                  "dimension" : {
                    "type" : "constant",
                    "value" : 12
                  }
                },
                "reference" : "58c1bef6-40ad-429d-b3c0-60c68350ca51",
                "hasValidationError" : false,
                "id" : "pbButton",
                "description" : ""
              }
            ],
            [
              {
                "type" : "component",
                "dimension" : {
                  "md" : 12,
                  "sm" : 12,
                  "xs" : 12,
                  "lg" : 12
                },
                "propertyValues" : {
                  "allowHTML" : {
                    "type" : "constant",
                    "value" : true
                  },
                  "allowHtml" : {
                    "type" : "constant",
                    "value" : true
                  },
                  "labelHidden" : {
                    "type" : "constant",
                    "value" : true
                  },
                  "hidden" : {
                    "type" : "expression",
                    "value" : "!formOutput._submitError.message"
                  },
                  "cssClasses" : {
                    "type" : "constant",
                    "value" : "alert alert-danger col-lg-6 col-lg-offset-3"
                  },
                  "label" : {
                    "type" : "interpolation"
                  },
                  "text" : {
                    "type" : "interpolation",
                    "value" : "<strong>Debug message</strong>\n<br/>\n{{formOutput._submitError.message}}\n{{submit_errors_list}}"
                  },
                  "alignment" : {
                    "type" : "constant",
                    "value" : "left"
                  },
                  "dimension" : {
                    "type" : "constant",
                    "value" : 12
                  }
                },
                "reference" : "627bfefa-0951-41a1-83a1-a5cf00aa657c",
                "hasValidationError" : false,
                "id" : "pbText",
                "description" : ""
              }
            ]
          ]
        }
      }
    ]
  ],
  "variables" : {
    "task" : {
      "type" : "url",
      "value" : [
        "../API/bpm/userTask/{{taskId}}"
      ],
      "exposed" : false
    },
    "submit_errors_list" : {
      "type" : "expression",
      "value" : [
        "if($data.formOutput && $data.formOutput._submitError && $data.formOutput._submitError.explanations){",
        "\tconst liElements = $data.formOutput._submitError.explanations",
        "\t\t.filter(cause => cause !== null)",
        "\t\t.map(cause => \"<li>\" + cause + \"</li>\")",
        "\t\t.join('');",
        "\tif(liElements){",
        "\t\treturn \"<ul>\" + liElements + \"</ul>\";",
        "\t}",
        "}"
      ],
      "exposed" : false
    },
    "formOutput" : {
      "type" : "expression",
      "value" : [
        "if( $data.pedido ){",
        "\treturn {",
        "\t\t//map pedido variable to expected task contract input",
        "\t\tpedidoInput: {",
        "\t\t\talteracao: $data.pedido.alteracao !== undefined ? $data.pedido.alteracao : null",
        "\t\t}",
        "\t}",
        "}"
      ],
      "exposed" : false
    },
    "context" : {
      "type" : "url",
      "value" : [
        "../API/bpm/userTask/{{taskId}}/context"
      ],
      "exposed" : false
    },
    "pedido" : {
      "type" : "url",
      "value" : [
        "../{{context.pedido_ref.link}}"
      ],
      "exposed" : false
    },
    "taskId" : {
      "type" : "urlparameter",
      "value" : [
        "id"
      ],
      "exposed" : false
    }
  },
  "assets" : [
    {
      "id" : "e87eb1dc-048a-4dc3-89aa-e6f150e9c8c7",
      "name" : "localization.json",
      "type" : "json",
      "order" : 0,
      "external" : false
    },
    {
      "id" : "372b9667-a8ff-4b7a-8d08-9bf1f8b85ee1",
      "name" : "style.css",
      "type" : "css",
      "order" : 0,
      "external" : false
    }
  ],
  "inactiveAssets" : [ ],
  "webResources" : [ ],
  "hasValidationError" : false
}